mybbs/__init__.py
mybbs/__main__.py
mybbs/bbs_client.py
bbs_client-0.1.0.dist-info/METADATA
bbs_client-0.1.0.dist-info/WHEEL
bbs_client-0.1.0.dist-info/entry_points.txt
bbs_client-0.1.0.dist-info/top_level.txt
bbs_client-0.1.0.dist-info/RECORD
