Metadata-Version: 2.4
Name: bbs-client
Version: 0.1.0
Summary: MyBBS client
Requires-Python: >=3.9
